vsix_url_generator/__init__.py
vsix_url_generator/generator.py
vsix_url_generator-0.1.0.dist-info/METADATA
vsix_url_generator-0.1.0.dist-info/WHEEL
vsix_url_generator-0.1.0.dist-info/RECORD
